buildahscript/_resolver.py
buildahscript/cli.py
buildahscript/metadata.py
buildahscript/modglobals.py
buildahscript/runner.py
buildahscript/venv.py
buildahscript-0.4.0.dist-info/entry_points.txt
buildahscript-0.4.0.dist-info/LICENSE
buildahscript-0.4.0.dist-info/WHEEL
buildahscript-0.4.0.dist-info/METADATA
buildahscript-0.4.0.dist-info/RECORD
