Metadata-Version: 2.1
Name: buildahscript
Version: 0.4.0
Summary: Tool for buildah scripts
Home-page: https://buildahscript.github.io/
Author: Jamie Bliss
Author-email: jamie@ivyleav.es
Requires-Python: >=3.7,<4.0
Classifier: Programming Language :: Python :: 3
Classifier: Programming Language :: Python :: 3.7
Classifier: Programming Language :: Python :: 3.8
Project-URL: Repository, https://github.com/buildahscript/buildahscript-py
